{
  "accentColor": "{{appsmith.theme.colors.primaryColor}}",
  "animateLoading": true,
  "borderColor": "#E0DEDE",
  "borderRadius": "{{appsmith.theme.borderRadius.appBorderRadius}}",
  "borderWidth": "1",
  "bottomRow": 29,
  "boxShadow": "{{appsmith.theme.boxShadow.appBoxShadow}}",
  "canFreezeColumn": true,
  "childStylesheet": {
    "button": {
      "borderRadius": "{{appsmith.theme.borderRadius.appBorderRadius}}",
      "boxShadow": "none",
      "buttonColor": "{{appsmith.theme.colors.primaryColor}}"
    },
    "editActions": {
      "discardBorderRadius": "{{appsmith.theme.borderRadius.appBorderRadius}}",
      "discardButtonColor": "{{appsmith.theme.colors.primaryColor}}",
      "saveBorderRadius": "{{appsmith.theme.borderRadius.appBorderRadius}}",
      "saveButtonColor": "{{appsmith.theme.colors.primaryColor}}"
    },
    "iconButton": {
      "borderRadius": "{{appsmith.theme.borderRadius.appBorderRadius}}",
      "boxShadow": "none",
      "buttonColor": "{{appsmith.theme.colors.primaryColor}}"
    },
    "menuButton": {
      "borderRadius": "{{appsmith.theme.borderRadius.appBorderRadius}}",
      "boxShadow": "none",
      "menuColor": "{{appsmith.theme.colors.primaryColor}}"
    }
  },
  "columnOrder": [
    "INTEGER_COL",
    "VARCHAR_COL",
    "BOOLEAN_COL",
    "DATE_COL"
  ],
  "columnUpdatedAt": 1720181635954,
  "columnWidthMap": {},
  "defaultPageSize": 0,
  "defaultSelectedRowIndex": 0,
  "defaultSelectedRowIndices": [
    0
  ],
  "delimiter": ",",
  "displayName": "Table",
  "dynamicBindingPathList": [
    {
      "key": "tableData"
    },
    {
      "key": "accentColor"
    },
    {
      "key": "borderRadius"
    },
    {
      "key": "boxShadow"
    },
    {
      "key": "primaryColumns.INTEGER_COL.computedValue"
    },
    {
      "key": "primaryColumns.VARCHAR_COL.computedValue"
    },
    {
      "key": "primaryColumns.BOOLEAN_COL.computedValue"
    },
    {
      "key": "primaryColumns.DATE_COL.computedValue"
    }
  ],
  "dynamicPropertyPathList": [],
  "dynamicTriggerPathList": [],
  "enableClientSideSearch": true,
  "flexVerticalAlignment": "start",
  "hideCard": false,
  "horizontalAlignment": "LEFT",
  "iconSVG": "/static/media/icon.cf625df24d42d0de4d06cba559b3c327.svg",
  "inlineEditingSaveOption": "ROW_LEVEL",
  "isDeprecated": false,
  "isLoading": false,
  "isSortable": true,
  "isVisible": true,
  "isVisibleDownload": true,
  "isVisibleFilters": false,
  "isVisiblePagination": true,
  "isVisibleSearch": true,
  "key": "zu95h1i493",
  "label": "Data",
  "leftColumn": 0,
  "minWidth": 450,
  "mobileBottomRow": 29,
  "mobileLeftColumn": 0,
  "mobileRightColumn": 34,
  "mobileTopRow": 1,
  "needsErrorInfo": false,
  "needsHeightForContent": true,
  "onCanvasUI": {
    "disableParentSelection": false,
    "focusBGCSSVar": "--on-canvas-ui-widget-focus",
    "focusColorCSSVar": "--on-canvas-ui-widget-selection",
    "selectionBGCSSVar": "--on-canvas-ui-widget-selection",
    "selectionColorCSSVar": "--on-canvas-ui-widget-focus"
  },
  "parentId": "0",
  "parentRowSpace": 10,
  "primaryColumns": {
    "BOOLEAN_COL": {
      "alias": "BOOLEAN_COL",
      "allowCellWrapping": false,
      "allowSameOptionsInNewRow": true,
      "cellBackground": "",
      "columnType": "checkbox",
      "computedValue": "{{Table1.processedTableData.map((currentRow, currentIndex) => ( currentRow[\"BOOLEAN_COL\"]))}}",
      "currencyCode": "USD",
      "decimals": 0,
      "enableFilter": true,
      "enableSort": true,
      "fontStyle": "",
      "horizontalAlignment": "LEFT",
      "id": "BOOLEAN_COL",
      "index": 2,
      "isCellEditable": false,
      "isCellVisible": true,
      "isDerived": false,
      "isDisabled": false,
      "isDiscardVisible": true,
      "isEditable": false,
      "isSaveVisible": true,
      "isVisible": true,
      "label": "BOOLEAN_COL",
      "notation": "standard",
      "originalId": "BOOLEAN_COL",
      "sticky": "",
      "textColor": "",
      "textSize": "0.875rem",
      "thousandSeparator": true,
      "validation": {},
      "verticalAlignment": "CENTER",
      "width": 150
    },
    "DATE_COL": {
      "alias": "DATE_COL",
      "allowCellWrapping": false,
      "allowSameOptionsInNewRow": true,
      "cellBackground": "",
      "columnType": "number",
      "computedValue": "{{Table1.processedTableData.map((currentRow, currentIndex) => ( currentRow[\"DATE_COL\"]))}}",
      "currencyCode": "USD",
      "decimals": 0,
      "enableFilter": true,
      "enableSort": true,
      "fontStyle": "",
      "horizontalAlignment": "LEFT",
      "id": "DATE_COL",
      "index": 3,
      "isCellEditable": false,
      "isCellVisible": true,
      "isDerived": false,
      "isDisabled": false,
      "isDiscardVisible": true,
      "isEditable": false,
      "isSaveVisible": true,
      "isVisible": true,
      "label": "DATE_COL",
      "notation": "standard",
      "originalId": "DATE_COL",
      "sticky": "",
      "textColor": "",
      "textSize": "0.875rem",
      "thousandSeparator": true,
      "validation": {},
      "verticalAlignment": "CENTER",
      "width": 150
    },
    "INTEGER_COL": {
      "alias": "INTEGER_COL",
      "allowCellWrapping": false,
      "allowSameOptionsInNewRow": true,
      "cellBackground": "",
      "columnType": "number",
      "computedValue": "{{Table1.processedTableData.map((currentRow, currentIndex) => ( currentRow[\"INTEGER_COL\"]))}}",
      "currencyCode": "USD",
      "decimals": 0,
      "enableFilter": true,
      "enableSort": true,
      "fontStyle": "",
      "horizontalAlignment": "LEFT",
      "id": "INTEGER_COL",
      "index": 0,
      "isCellEditable": false,
      "isCellVisible": true,
      "isDerived": false,
      "isDisabled": false,
      "isDiscardVisible": true,
      "isEditable": false,
      "isSaveVisible": true,
      "isVisible": true,
      "label": "INTEGER_COL",
      "notation": "standard",
      "originalId": "INTEGER_COL",
      "sticky": "",
      "textColor": "",
      "textSize": "0.875rem",
      "thousandSeparator": true,
      "validation": {},
      "verticalAlignment": "CENTER",
      "width": 150
    },
    "VARCHAR_COL": {
      "alias": "VARCHAR_COL",
      "allowCellWrapping": false,
      "allowSameOptionsInNewRow": true,
      "cellBackground": "",
      "columnType": "text",
      "computedValue": "{{Table1.processedTableData.map((currentRow, currentIndex) => ( currentRow[\"VARCHAR_COL\"]))}}",
      "currencyCode": "USD",
      "decimals": 0,
      "enableFilter": true,
      "enableSort": true,
      "fontStyle": "",
      "horizontalAlignment": "LEFT",
      "id": "VARCHAR_COL",
      "index": 1,
      "isCellEditable": false,
      "isCellVisible": true,
      "isDerived": false,
      "isDisabled": false,
      "isDiscardVisible": true,
      "isEditable": false,
      "isSaveVisible": true,
      "isVisible": true,
      "label": "VARCHAR_COL",
      "notation": "standard",
      "originalId": "VARCHAR_COL",
      "sticky": "",
      "textColor": "",
      "textSize": "0.875rem",
      "thousandSeparator": true,
      "validation": {},
      "verticalAlignment": "CENTER",
      "width": 150
    }
  },
  "renderMode": "CANVAS",
  "responsiveBehavior": "fill",
  "rightColumn": 64,
  "searchKey": "",
  "tableData": "{{Query4.data}}",
  "tags": [
    "Suggested",
    "Display"
  ],
  "textSize": "0.875rem",
  "thumbnailSVG": "https://release-appcdn.appsmith.com/static/media/thumbnail.d0492f06681daa69baf92b07d3829dfc.svg",
  "topRow": 1,
  "totalRecordsCount": 0,
  "type": "TABLE_WIDGET_V2",
  "version": 2,
  "verticalAlignment": "CENTER",
  "widgetId": "q08z3yysu2",
  "widgetName": "Table1"
}